[
	{
		"model": "iot.Voltage",
		"pk": 1,
		"fields": {
		"microComputer" : 1,
		"operatingVoltage" : 5.0,
		"inputVoltageRecommended" : "7-12,
		"IOCurrentMax" : "6-20",
		"DCCurrentfor3_3VPin" : 50",
		"powerRatings" : "",
		"powerSource" : ""
	}
},
	{
		"model": "iot.Voltage",
		"pk": 2,
		"fields": {
		"microComputer" : 2,
		"operatingVoltage" : 5.0,
		"inputVoltageRecommended" : "7-12,
		"IOCurrentMax" : "6-20",
		"DCCurrentfor3_3VPin" : 50",
		"powerRatings" : "",
		"powerSource" : ""
	}
},
	{
		"model": "iot.Voltage",
		"pk": 3,
		"fields": {
		"microComputer" : 3,
		"operatingVoltage" : 3.3,
		"inputVoltageRecommended" : "7-12,
		"IOCurrentMax" : "6-16",
		"DCCurrentfor3_3VPin" : 800",
		"powerRatings" : "",
		"powerSource" : ""
	}
},
	{
		"model": "iot.Voltage",
		"pk": 4,
		"fields": {
		"microComputer" : 4,
		"operatingVoltage" : 5.0,
		"inputVoltageRecommended" : "5,
		"IOCurrentMax" : "0",
		"DCCurrentfor3_3VPin" : 50",
		"powerRatings" : "",
		"powerSource" : ""
	}
}
]
